ussr/__init__.py
ussr/reencoder.py
ussr/test.py
ussr-0.1.dist-info/LICENSE
ussr-0.1.dist-info/METADATA
ussr-0.1.dist-info/WHEEL
ussr-0.1.dist-info/top_level.txt
ussr-0.1.dist-info/RECORD
